wnyc_recommender/fetcher
wnyc_recommender/engine
wnyc_recommender
wnyc_recommender/server
wnyc_recommender/__init__
