Metadata-Version: 1.0
Name: wnyc-recommender
Version: 0.0.3
Summary: Recommender
Home-page: https://github.com/wnyc/recommender
Author: Adam DePrince
Author-email: adeprince@nypublicradio.org
License: GPL
Platform: UNKNOWN
